{
    "data": {
        "has_more": true,
        "search_sh_sku_info_list": [
            {
                "authentication_method": "\u0436\u2014\u00a0\u0438\u00ae\u04e8\u0438\u049c\u0492",
                "brand_id": 3,
                "brand_name": "\u0435\u0498\u201d\u0439\u00a9\u00b0",
                "brand_source_city_name": "\u0436\u04ef\u04b0\u0436\u04b1\u04af",
                "car_age": "",
                "car_id": 25086,
                "car_mileage": "",
                "car_name": "S 320 L",
                "car_source_city_name": "\u0436\u04ef\u04b0\u0436\u04b1\u04af",
                "car_source_type": "\u0438\u04ae\u04d8\u0438\u0497\u0498",
                "car_year": 2018,
                "group_id": 0,
                "group_id_str": "0",
                "image": "https://p5-auto-sign.dcarimg.com/tos-cn-i-f042mdwyw7/aa91dfc0b712413eb21dbd18fec59697~tplv-f042mdwyw7-auto-webp:480:0.jpg?rk3s=4892dee6&x-expires=1722650987&x-signature=%2FYULmm6xk0GaOrsqIO5S1AQUeQ8%3D",
                "is_self_trade": false,
                "is_video": false,
                "official_hint_bar": "",
                "official_price": "\u043e\u201c\u0408\u043e\u04b8\u00ab.\u043e\u201d\u0499\u043e\u201c\u0408\u043e\u0497\u04a0",
                "platform_type": 0,
                "related_video_thumb": "",
                "series_id": 224,
                "series_name": "\u0435\u0498\u201d\u0439\u00a9\u00b0S\u0437\u04d9\u00a7",
                "sh_price": "\u043e\u0497\u049b\u043e\u04b8\u00ab.\u043e\u0497\u2116\u043e\u0497\u2116\u043e\u0497\u04a0",
                "shop_id": "37969",
                "sku_id": 13498925,
                "special_tags": null,
                "spu_id": 13058963,
                "sub_title": "\u043e\u2018\u0408\u043e\u0497\u2116\u043e\u2022\u04a2\u043e\u201c\u0408\u043e\u201d\u0498 | \u043e\u201d\u0499.\u043e\u0497\u049b\u043e\u0497\u2116\u043e\u0497\u04a0\u043e\u2019\u2019\u043e\u2019\u0401",
                "tags": [],
                "tags_v2": null,
                "title": "\u0435\u0498\u201d\u0439\u00a9\u00b0S\u0437\u04d9\u00a7 2018\u0436\u00ac\u04ab S 320 L",
                "transfer_cnt": 1
            },
            {
                "authentication_method": "\u0436\u2014\u00a0\u0438\u00ae\u04e8\u0438\u049c\u0492",
                "brand_id": 2,
                "brand_name": "\u0435\u0498\u0498\u0438\u049d\u04d8",
                "brand_source_city_name": "\u0439\u04ee\u045e\u0435\u04b8\u00b0",
                "car_age": "",
                "car_id": 76917,
                "car_mileage": "",
                "car_name": "A8L 45 TFSI quattro\u0438\u04b1\u04d8\u0435\u049a\u04ba\u0435\u04bb\u04e2",
                "car_source_city_name": "\u0439\u04ee\u045e\u0435\u04b8\u00b0",
                "car_source_type": "\u0438\u04ae\u04d8\u0438\u0497\u0498",
                "car_year": 2023,
                "group_id": 0,
                "group_id_str": "0",
                "image": "https://p5-auto-sign.dcarimg.com/tos-cn-i-f042mdwyw7/bc55c26cf0bb4dfb9e450c17a8e37271~tplv-f042mdwyw7-auto-webp:480:0.jpg?rk3s=4892dee6&x-expires=1722650987&x-signature=SF6Y3A300TO1U8QoQsTDNDTyeIE%3D",
                "is_self_trade": false,
                "is_video": false,
                "official_hint_bar": "",
                "official_price": "\u043e\u201c\u0408\u043e\u2018\u0408.\u043e\u2018\u049b\u043e\u201c\u0408\u043e\u0497\u04a0",
                "platform_type": 0,
                "related_video_thumb": "",
                "series_id": 82,
                "series_name": "\u0435\u0498\u0498\u0438\u049d\u04d8A8",
                "sh_price": "\u043e\u0497\u2018\u043e\u0497\u049b.\u043e\u201c\u0408\u043e\u0497\u2116\u043e\u0497\u04a0",
                "shop_id": "44961",
                "sku_id": 15534440,
                "special_tags": null,
                "spu_id": 15054810,
                "sub_title": "\u043e\u2018\u0408\u043e\u0497\u2116\u043e\u2018\u0408\u043e\u2019\u049b\u043e\u201d\u0498 | \u043e\u2022\u04a2.\u043e\u201c\u0408\u043e\u2018\u049b\u043e\u0497\u04a0\u043e\u2019\u2019\u043e\u2019\u0401",
                "tags": [
                    {
                        "background_color": "rgb(242,244,250)",
                        "logo": "",
                        "text": "\u0435\u04ae\u04b6\u0436\u2013\u00b0\u0438\u04aa\u04b0",
                        "text_color": "rgb(99,102,117)"
                    }
                ],
                "tags_v2": null,
                "title": "\u0435\u0498\u0498\u0438\u049d\u04d8A8 2023\u0436\u00ac\u04ab A8L 45 TFSI quattro\u0438\u04b1\u04d8\u0435\u049a\u04ba\u0435\u04bb\u04e2",
                "transfer_cnt": 0
            },
            {
                "authentication_method": "\u0436\u2014\u00a0\u0438\u00ae\u04e8\u0438\u049c\u0492",
                "brand_id": 11,
                "brand_name": "\u0437\u04ba\u00b0\u0434\u00bb\u0408",
                "brand_source_city_name": "\u0436\u0451\u00a9\u0435\u00b7\u04bb",
                "car_age": "",
                "car_id": 25003,
                "car_mileage": "",
                "car_name": "1.4L \u0438\u04ae\u04d8\u0435\u04a0\u0401\u0438\u00b7\u0493\u0434\u04d9\u00ab\u0437\u04af\u04b2 \u0435\u04e3\u04aaV",
                "car_source_city_name": "\u0436\u0451\u00a9\u0435\u00b7\u04bb",
                "car_source_type": "\u0438\u04ae\u04d8\u0438\u0497\u0498",
                "car_year": 2017,
                "group_id": 7390263001284575271,
                "group_id_str": "7390263001284575271",
                "image": "https://p5-auto-sign.dcarimg.com/tos-cn-i-f042mdwyw7/383be8105bb1440b9a7872c589960a19~tplv-f042mdwyw7-auto-webp:480:0.jpg?rk3s=4892dee6&x-expires=1722650987&x-signature=QxCrA6vGPKLcM1pdyRSy1uOEQio%3D",
                "is_self_trade": false,
                "is_video": true,
                "official_hint_bar": "",
                "official_price": "\u043e\u201d\u0499.\u043e\u0497\u2018\u043e\u2018\u049b\u043e\u0497\u04a0",
                "platform_type": 0,
                "related_video_thumb": "",
                "series_id": 1304,
                "series_name": "\u0437\u2018\u04bb\u0437\u04d9\u0456",
                "sh_price": "\u043e\u2019\u049b.\u043e\u2018\u0408\u043e\u201c\u0408\u043e\u0497\u04a0",
                "shop_id": "48350",
                "sku_id": 15490781,
                "special_tags": null,
                "spu_id": 15012183,
                "sub_title": "\u043e\u2018\u0408\u043e\u0497\u2116\u043e\u2022\u04a2\u043e\u201c\u0408\u043e\u201d\u0498 | \u043e\u201c\u0408\u043e\u0497\u04a0\u043e\u2019\u2019\u043e\u2019\u0401",
                "tags": [],
                "tags_v2": null,
                "title": "\u0437\u2018\u04bb\u0437\u04d9\u0456 2017\u0436\u00ac\u04ab 1.4L \u0438\u04ae\u04d8\u0435\u04a0\u0401\u0438\u00b7\u0493\u0434\u04d9\u00ab\u0437\u04af\u04b2 \u0435\u04e3\u04aaV",
                "transfer_cnt": 0
            },
            {
                "authentication_method": "\u0436\u2014\u00a0\u0438\u00ae\u04e8\u0438\u049c\u0492",
                "brand_id": 13,
                "brand_name": "\u0438\u04e9\u00b7\u0434\u04d9\u04a1",
                "brand_source_city_name": "\u0436\u04e9\u04ba\u0435\u049a\u2014",
                "car_age": "",
                "car_id": 50937,
                "car_mileage": "",
                "car_name": "1.5L IVT \u0436\u2014\u00b6\u0435\u00b0\u04a1\u0437\u04af\u04b2",
                "car_source_city_name": "\u0436\u04e9\u04ba\u0435\u049a\u2014",
                "car_source_type": "\u0438\u04ae\u04d8\u0438\u0497\u0498",
                "car_year": 2021,
                "group_id": 0,
                "group_id_str": "0",
                "image": "https://p5-auto-sign.dcarimg.com/tos-cn-i-f042mdwyw7/d55ff8e01128434baebbb666babdef46~tplv-f042mdwyw7-auto-webp:480:0.jpg?rk3s=4892dee6&x-expires=1722650987&x-signature=Bm9Cr%2FvoKcRCPIto2e3j3r0AD2Y%3D",
                "is_self_trade": false,
                "is_video": false,
                "official_hint_bar": "",
                "official_price": "\u043e\u2022\u04a2\u043e\u2022\u04a2.\u043e\u0497\u049b\u043e\u201c\u0408\u043e\u0497\u04a0",
                "platform_type": 0,
                "related_video_thumb": "",
                "series_id": 1116,
                "series_name": "\u0438\u04e9\u00b7\u0434\u04d9\u04a1K3",
                "sh_price": "\u043e\u201d\u0499.\u043e\u2022\u04a2\u043e\u201c\u0408\u043e\u0497\u04a0",
                "shop_id": "86073",
                "sku_id": 15489051,
                "special_tags": null,
                "spu_id": 15010486,
                "sub_title": "\u043e\u2018\u0408\u043e\u0497\u2116\u043e\u2018\u0408\u043e\u2022\u04a2\u043e\u201d\u0498 | \u043e\u201d\u0499.\u043e\u201c\u0408\u043e\u0497\u2116\u043e\u0497\u04a0\u043e\u2019\u2019\u043e\u2019\u0401",
                "tags": [],
                "tags_v2": null,
                "title": "\u0438\u04e9\u00b7\u0434\u04d9\u04a1K3 2021\u0436\u00ac\u04ab 1.5L IVT \u0436\u2014\u00b6\u0435\u00b0\u04a1\u0437\u04af\u04b2",
                "transfer_cnt": 0
            },
            {
                "authentication_method": "\u0436\u2014\u00a0\u0438\u00ae\u04e8\u0438\u049c\u0492",
                "brand_id": 7,
                "brand_name": "\u0437\u04b0\u04b8\u0437\u04af\u2116",
                "brand_source_city_name": "\u0438\u04e2\u04b8\u0435\u00b7\u04bb",
                "car_age": "",
                "car_id": 8576,
                "car_mileage": "",
                "car_name": "\u0434\u0451\u04e8\u0435\u04ba\u045e 1.5L \u0438\u04ae\u04d8\u0435\u04a0\u0401\u0438\u049d\u0497\u0435\u04a0\u0401\u0435\u04bb\u04e2",
                "car_source_city_name": "\u0438\u04e2\u04b8\u0435\u00b7\u04bb",
                "car_source_type": "\u0438\u04ae\u04d8\u0438\u0497\u0498",
                "car_year": 2011,
                "group_id": 0,
                "group_id_str": "0",
                "image": "https://p5-auto-sign.dcarimg.com/tos-cn-i-f042mdwyw7/9faeb20f86a2497da0f8f40c7a3175b2~tplv-f042mdwyw7-auto-webp:480:0.jpg?rk3s=4892dee6&x-expires=1722650987&x-signature=ks%2F9FKs6nKo9IskTlcfIIsA2vPk%3D",
                "is_self_trade": false,
                "is_video": false,
                "official_hint_bar": "",
                "official_price": "\u043e\u2022\u04a2\u043e\u0497\u2116.\u043e\u2018\u049b\u043e\u2018\u049b\u043e\u0497\u04a0",
                "platform_type": 0,
                "related_video_thumb": "",
                "series_id": 576,
                "series_name": "\u0435\u04b3\u04af\u0435\u2116\u0499\u0435\u049a\u04ba",
                "sh_price": "\u043e\u2018\u0408.\u043e\u2018\u0408\u043e\u201c\u0408\u043e\u0497\u04a0",
                "shop_id": "59246",
                "sku_id": 15452454,
                "special_tags": null,
                "spu_id": 14974792,
                "sub_title": "\u043e\u2018\u0408\u043e\u0497\u2116\u043e\u2022\u04a2\u043e\u2022\u04a2\u043e\u201d\u0498 | \u043e\u201c\u0408.\u043e\u0497\u2018\u043e\u0497\u2116\u043e\u0497\u04a0\u043e\u2019\u2019\u043e\u2019\u0401",
                "tags": [],
                "tags_v2": null,
                "title": "\u0435\u04b3\u04af\u0435\u2116\u0499\u0435\u049a\u04ba 2011\u0436\u00ac\u04ab \u0434\u0451\u04e8\u0435\u04ba\u045e 1.5L \u0438\u04ae\u04d8\u0435\u04a0\u0401\u0438\u049d\u0497\u0435\u04a0\u0401\u0435\u04bb\u04e2",
                "transfer_cnt": 0
            },
            {
                "authentication_method": "\u0436\u2014\u00a0\u0438\u00ae\u04e8\u0438\u049c\u0492",
                "brand_id": 16,
                "brand_name": "\u0436\u049c\u201d\u0434\u04d9\u04a1\u0438\u049d\u04d8",
                "brand_source_city_name": "\u0434\u0451\u04a3\u0438\u04ba\u04bb",
                "car_age": "",
                "car_id": 4372,
                "car_mileage": "",
                "car_name": "2.0L \u0436\u04af\u04e2\u0435\u04a0\u0401\u0438\u04b1\u04d8\u0435\u049a\u04ba\u0435\u04bb\u04e2",
                "car_source_city_name": "\u043e\u2019\u04b9\u0438\u04ba\u04bb",
                "car_source_type": "\u0438\u04ae\u04d8\u0438\u0497\u0498",
                "car_year": 2012,
                "group_id": 0,
                "group_id_str": "0",
                "image": "https://p5-auto-sign.dcarimg.com/tos-cn-i-f042mdwyw7/42be411caa2046e48722f8c2f41f3bc1~tplv-f042mdwyw7-auto-webp:480:0.jpg?rk3s=4892dee6&x-expires=1722650987&x-signature=w6vL%2BYM36kk4C5PbYbVa3hxYdcA%3D",
                "is_self_trade": false,
                "is_video": false,
                "official_hint_bar": "",
                "official_price": "\u043e\u201c\u0408.\u043e\u2018\u049b\u043e\u2018\u049b\u043e\u0497\u04a0",
                "platform_type": 0,
                "related_video_thumb": "",
                "series_id": 317,
                "series_name": "\u0436\u049c\u201d\u0434\u04d9\u04a1\u0438\u049d\u04d8S6",
                "sh_price": "\u043e\u0497\u2116.\u043e\u04b8\u00ab\u043e\u201d\u0499\u043e\u0497\u04a0",
                "shop_id": "65368",
                "sku_id": 15388118,
                "special_tags": null,
                "spu_id": 14911703,
                "sub_title": "\u043e\u2018\u0408\u043e\u0497\u2116\u043e\u2022\u04a2\u043e\u2018\u0408\u043e\u201d\u0498 | \u043e\u2022\u04a2\u043e\u2022\u04a2\u043e\u0497\u04a0\u043e\u2019\u2019\u043e\u2019\u0401",
                "tags": [],
                "tags_v2": null,
                "title": "\u0436\u049c\u201d\u0434\u04d9\u04a1\u0438\u049d\u04d8S6 2012\u0436\u00ac\u04ab 2.0L \u0436\u04af\u04e2\u0435\u04a0\u0401\u0438\u04b1\u04d8\u0435\u049a\u04ba\u0435\u04bb\u04e2",
                "transfer_cnt": 1
            },
            {
                "authentication_method": "\u0436\u2014\u00a0\u0438\u00ae\u04e8\u0438\u049c\u0492",
                "brand_id": 4,
                "brand_name": "\u0435\u00ae\u049b\u0439\u00a9\u00ac",
                "brand_source_city_name": "\u0436\u04e9\u04ba\u0435\u049a\u2014",
                "car_age": "",
                "car_id": 41043,
                "car_mileage": "",
                "car_name": "525Li \u0438\u04b1\u04d8\u0435\u049a\u04ba\u0435\u0498\u2014\u0438\u0408\u2026",
                "car_source_city_name": "\u0436\u04e9\u04ba\u0435\u049a\u2014",
                "car_source_type": "\u0438\u04ae\u04d8\u0438\u0497\u0498",
                "car_year": 2020,
                "group_id": 0,
                "group_id_str": "0",
                "image": "https://p5-auto-sign.dcarimg.com/tos-cn-i-f042mdwyw7/166444cee6ef4d66885f2cdbd1283757~tplv-f042mdwyw7-auto-webp:480:0.jpg?rk3s=4892dee6&x-expires=1722650987&x-signature=wfyZqWZ4ldn9L0jiI9CDP6D28ws%3D",
                "is_self_trade": false,
                "is_video": false,
                "official_hint_bar": "",
                "official_price": "\u043e\u0497\u049b\u043e\u2018\u0408.\u043e\u201d\u0499\u043e\u2018\u049b\u043e\u0497\u04a0",
                "platform_type": 0,
                "related_video_thumb": "",
                "series_id": 146,
                "series_name": "\u0435\u00ae\u049b\u0439\u00a9\u00ac5\u0437\u0456\u00bb",
                "sh_price": "\u043e\u2018\u0408\u043e\u2019\u049b.\u043e\u0497\u2116\u043e\u0497\u2116\u043e\u0497\u04a0",
                "shop_id": "62442",
                "sku_id": 15377002,
                "special_tags": null,
                "spu_id": 14900928,
                "sub_title": "\u043e\u2018\u0408\u043e\u0497\u2116\u043e\u2018\u0408\u043e\u0497\u2116\u043e\u201d\u0498 | \u043e\u201d\u0499.\u043e\u0497\u2018\u043e\u0497\u2116\u043e\u0497\u04a0\u043e\u2019\u2019\u043e\u2019\u0401",
                "tags": [],
                "tags_v2": null,
                "title": "\u0435\u00ae\u049b\u0439\u00a9\u00ac5\u0437\u0456\u00bb 2020\u0436\u00ac\u04ab 525Li \u0438\u04b1\u04d8\u0435\u049a\u04ba\u0435\u0498\u2014\u0438\u0408\u2026",
                "transfer_cnt": 1
            },
            {
                "authentication_method": "\u0435\u00ae\u04b3\u0436\u2013\u2116\u0438\u00ae\u04e8\u0438\u049c\u0492",
                "brand_id": 2,
                "brand_name": "\u0435\u0498\u0498\u0438\u049d\u04d8",
                "brand_source_city_name": "\u0436\u0458\u0456\u0435\u00b7\u04bb",
                "car_age": "",
                "car_id": 79586,
                "car_mileage": "",
                "car_name": "35 TFSI \u0436\u2014\u00b6\u0435\u00b0\u04a1\u0435\u04a0\u0401\u0436\u201e\u04b9\u0435\u04bb\u04e2",
                "car_source_city_name": "\u0436\u0458\u0456\u0435\u00b7\u04bb",
                "car_source_type": "\u0438\u04ae\u04d8\u0438\u0497\u0498",
                "car_year": 2023,
                "group_id": 0,
                "group_id_str": "0",
                "image": "https://p5-auto-sign.dcarimg.com/tos-cn-i-f042mdwyw7/8daccd875b43494599bf9870cb68cdf4~tplv-f042mdwyw7-auto-webp:480:0.jpg?rk3s=4892dee6&x-expires=1722650987&x-signature=7FJMUOORxO%2BAsMA2WnyfNd7WUlI%3D",
                "is_self_trade": false,
                "is_video": false,
                "official_hint_bar": "",
                "official_price": "\u043e\u2018\u0408\u043e\u2018\u049b.\u043e\u2018\u0408\u043e\u201c\u0408\u043e\u0497\u04a0",
                "platform_type": 0,
                "related_video_thumb": "",
                "series_id": 100,
                "series_name": "\u0435\u0498\u0498\u0438\u049d\u04d8Q3",
                "sh_price": "\u043e\u2022\u04a2\u043e\u201d\u0499.\u043e\u2018\u049b\u043e\u201c\u0408\u043e\u0497\u04a0",
                "shop_id": "46362",
                "sku_id": 15317311,
                "special_tags": null,
                "spu_id": 14842471,
                "sub_title": "\u043e\u2018\u0408\u043e\u0497\u2116\u043e\u2018\u0408\u043e\u2019\u049b\u043e\u201d\u0498 | \u043e\u2018\u0408.\u043e\u2018\u0408\u043e\u0497\u2116\u043e\u0497\u04a0\u043e\u2019\u2019\u043e\u2019\u0401",
                "tags": [
                    {
                        "background_color": "rgb(242,244,250)",
                        "logo": "",
                        "text": "\u0435\u04ae\u04b6\u0436\u2013\u00b0\u0438\u04aa\u04b0",
                        "text_color": "rgb(99,102,117)"
                    }
                ],
                "tags_v2": null,
                "title": "\u0435\u0498\u0498\u0438\u049d\u04d8Q3 2023\u0436\u00ac\u04ab 35 TFSI \u0436\u2014\u00b6\u0435\u00b0\u04a1\u0435\u04a0\u0401\u0436\u201e\u04b9\u0435\u04bb\u04e2",
                "transfer_cnt": 1
            },
            {
                "authentication_method": "\u0439\u049b\u04bb\u0435\u00ae\u04b3\u0436\u2013\u2116\u0438\u00ae\u04e8\u0438\u049c\u0492",
                "brand_id": 3,
                "brand_name": "\u0435\u0498\u201d\u0439\u00a9\u00b0",
                "brand_source_city_name": "\u0436\u04b3\u04b6\u0436\u04b3\u04ba",
                "car_age": "",
                "car_id": 39813,
                "car_mileage": "",
                "car_name": "GLC 300 L 4MATIC \u0435\u04a0\u0401\u0436\u201e\u04b9\u0435\u04bb\u04e2",
                "car_source_city_name": "\u0436\u04b3\u04b6\u043e\u2019\u04a2",
                "car_source_type": "\u0438\u04ae\u04d8\u0438\u0497\u0498",
                "car_year": 2020,
                "group_id": 0,
                "group_id_str": "0",
                "image": "https://p5-auto-sign.dcarimg.com/tos-cn-i-f042mdwyw7/c39a07819569477d9f987295fdf0bd37~tplv-f042mdwyw7-auto-webp:480:0.jpg?rk3s=4892dee6&x-expires=1722650987&x-signature=c%2B%2F2MDudpg5qvPQHaUCVRHpIIJw%3D",
                "is_self_trade": false,
                "is_video": false,
                "official_hint_bar": "",
                "official_price": "\u043e\u0497\u049b\u043e\u0497\u049b.\u043e\u04b8\u00ab\u043e\u201c\u0408\u043e\u0497\u04a0",
                "platform_type": 0,
                "related_video_thumb": "",
                "series_id": 216,
                "series_name": "\u0435\u0498\u201d\u0439\u00a9\u00b0GLC",
                "sh_price": "\u043e\u2018\u0408\u043e\u0497\u2018.\u043e\u2018\u049b\u043e\u201c\u0408\u043e\u0497\u04a0",
                "shop_id": "35129",
                "sku_id": 15207585,
                "special_tags": null,
                "spu_id": 14735468,
                "sub_title": "\u043e\u2018\u0408\u043e\u0497\u2116\u043e\u2022\u04a2\u043e\u2018\u049b\u043e\u201d\u0498 | \u043e\u201c\u0408.\u043e\u201d\u0499\u043e\u0497\u2116\u043e\u0497\u04a0\u043e\u2019\u2019\u043e\u2019\u0401",
                "tags": [
                    {
                        "background_color": "rgba(179,125,18,0.1)",
                        "logo": "https://p3.dcarimg.com/img/tos-cn-i-dcdx/5f0015d5e1ee4547b51bc7544a06765c~noop.image",
                        "text": "\u0436\u0408\u0496\u0436\u04e9\u04e2\u0436\u04a0\u0498\u0435\u2018\u04a0",
                        "text_color": "rgba(179,125,18,1)"
                    }
                ],
                "tags_v2": null,
                "title": "\u0435\u0498\u201d\u0439\u00a9\u00b0GLC 2020\u0436\u00ac\u04ab GLC 300 L 4MATIC \u0435\u04a0\u0401\u0436\u201e\u04b9\u0435\u04bb\u04e2",
                "transfer_cnt": 1
            },
            {
                "authentication_method": "\u0436\u2014\u00a0\u0438\u00ae\u04e8\u0438\u049c\u0492",
                "brand_id": 61,
                "brand_name": "\u0436\u00a0\u04ae\u0438\u04ae\u0499",
                "brand_source_city_name": "\u0434\u0451\u04a0\u0436\u04e9\u00b7",
                "car_age": "",
                "car_id": 4685,
                "car_mileage": "",
                "car_name": "2.0L \u0438\u04ae\u04d8\u0435\u04a0\u0401\u0436\u04aa\u00ae\u0436\u04e9\u0492\u0437\u04af\u04b2",
                "car_source_city_name": "\u043e\u2018\u04b9\u043e\u0497\u04b1",
                "car_source_type": "\u0438\u04ae\u04d8\u0438\u0497\u0498",
                "car_year": 2013,
                "group_id": 7381060446112972854,
                "group_id_str": "7381060446112972854",
                "image": "https://p5-auto-sign.dcarimg.com/tos-cn-i-f042mdwyw7/ad8d9a6cea354beb8eea03ba047ea72f~tplv-f042mdwyw7-auto-webp:480:0.jpg?rk3s=4892dee6&x-expires=1722650987&x-signature=HjdlmxOqCqrijRGXndemxGu%2FxMs%3D",
                "is_self_trade": false,
                "is_video": true,
                "official_hint_bar": "",
                "official_price": "\u043e\u2022\u04a2\u043e\u201c\u0408.\u043e\u201d\u0499\u043e\u04b8\u00ab\u043e\u0497\u04a0",
                "platform_type": 0,
                "related_video_thumb": "",
                "series_id": 339,
                "series_name": "\u0436\u00a0\u04ae\u0438\u04ae\u04993008",
                "sh_price": "\u043e\u2018\u0408.\u043e\u2019\u049b\u043e\u0497\u2018\u043e\u0497\u04a0",
                "shop_id": "1315",
                "sku_id": 15201745,
                "special_tags": null,
                "spu_id": 14729630,
                "sub_title": "\u043e\u2018\u0408\u043e\u0497\u2116\u043e\u2022\u04a2\u043e\u2019\u049b\u043e\u201d\u0498 | \u043e\u201d\u0499.\u043e\u2018\u049b\u043e\u0497\u2116\u043e\u0497\u04a0\u043e\u2019\u2019\u043e\u2019\u0401",
                "tags": [],
                "tags_v2": null,
                "title": "\u0436\u00a0\u04ae\u0438\u04ae\u04993008 2013\u0436\u00ac\u04ab 2.0L \u0438\u04ae\u04d8\u0435\u04a0\u0401\u0436\u04aa\u00ae\u0436\u04e9\u0492\u0437\u04af\u04b2",
                "transfer_cnt": 0
            },
            {
                "authentication_method": "\u0436\u2014\u00a0\u0438\u00ae\u04e8\u0438\u049c\u0492",
                "brand_id": 59,
                "brand_name": "\u0437\u04d9\u045e\u0436\u2014\u2014",
                "brand_source_city_name": "\u0435\u0497\u04b2\u0438\u04ee\u0498",
                "car_age": "",
                "car_id": 55314,
                "car_mileage": "",
                "car_name": "2.0T \u0436\u04b7\u04d9\u0438\u0492\u201d\u0436\u2014\u2014\u0434\u04d9\u00ab\u0437\u04af\u04b2",
                "car_source_city_name": "\u0435\u0497\u04b2\u0438\u04ee\u0498",
                "car_source_type": "\u0438\u04ae\u04d8\u0438\u0497\u0498",
                "car_year": 2022,
                "group_id": 0,
                "group_id_str": "0",
                "image": "https://p5-auto-sign.dcarimg.com/tos-cn-i-f042mdwyw7/c03bbb7c15d9431ca8cd6b893ca76a83~tplv-f042mdwyw7-auto-webp:480:0.jpg?rk3s=4892dee6&x-expires=1722650987&x-signature=Hqw9HGoy8eX7NuRAJHrhkpGzbd8%3D",
                "is_self_trade": false,
                "is_video": false,
                "official_hint_bar": "",
                "official_price": "\u043e\u2022\u04a2\u043e\u2018\u049b.\u043e\u2018\u049b\u043e\u201c\u0408\u043e\u0497\u04a0",
                "platform_type": 0,
                "related_video_thumb": "",
                "series_id": 3159,
                "series_name": "\u0437\u04d9\u045e\u0436\u2014\u2014HS5",
                "sh_price": "\u043e\u2022\u04a2\u043e\u2022\u04a2.\u043e\u0497\u2018\u043e\u201c\u0408\u043e\u0497\u04a0",
                "shop_id": "54071",
                "sku_id": 14978702,
                "special_tags": null,
                "spu_id": 14510548,
                "sub_title": "\u043e\u2018\u0408\u043e\u0497\u2116\u043e\u2018\u0408\u043e\u2018\u0408\u043e\u201d\u0498 | \u043e\u0497\u049b.\u043e\u2022\u04a2\u043e\u0497\u2116\u043e\u0497\u04a0\u043e\u2019\u2019\u043e\u2019\u0401",
                "tags": [],
                "tags_v2": null,
                "title": "\u0437\u04d9\u045e\u0436\u2014\u2014HS5 2022\u0436\u00ac\u04ab 2.0T \u0436\u04b7\u04d9\u0438\u0492\u201d\u0436\u2014\u2014\u0434\u04d9\u00ab\u0437\u04af\u04b2",
                "transfer_cnt": 1
            },
            {
                "authentication_method": "\u0436\u2014\u00a0\u0438\u00ae\u04e8\u0438\u049c\u0492",
                "brand_id": 1,
                "brand_name": "\u0435\u04e8\u00a7\u0434\u0458\u2014",
                "brand_source_city_name": "\u0439\u2022\u049d\u0436\u0406\u04b7",
                "car_age": "",
                "car_id": 72132,
                "car_mileage": "",
                "car_name": "\u0435\u04ae\u04a2\u0436\u0451\u040eL 280TSI DSG\u0439\u2026\u00b7\u0438\u04ab\u0408\u0437\u04af\u04b2",
                "car_source_city_name": "\u043e\u04b8\u00bb\u0436\u0406\u04b7",
                "car_source_type": "\u0438\u04ae\u04d8\u0438\u0497\u0498",
                "car_year": 2022,
                "group_id": 0,
                "group_id_str": "0",
                "image": "https://p5-auto-sign.dcarimg.com/tos-cn-i-f042mdwyw7/bfdb1b0016f04e8da6d69deaf303f100~tplv-f042mdwyw7-auto-webp:480:0.jpg?rk3s=4892dee6&x-expires=1722650987&x-signature=ktwXnlyIega4iBZeRVTavMe0SKQ%3D",
                "is_self_trade": false,
                "is_video": false,
                "official_hint_bar": "",
                "official_price": "\u043e\u2022\u04a2\u043e\u04b8\u00ab.\u043e\u0497\u2116\u043e\u2018\u049b\u043e\u0497\u04a0",
                "platform_type": 0,
                "related_video_thumb": "",
                "series_id": 397,
                "series_name": "\u0435\u04ae\u04a2\u0436\u0451\u040e",
                "sh_price": "\u043e\u2022\u04a2\u043e\u0497\u2116.\u043e\u201d\u0499\u043e\u0497\u2116\u043e\u0497\u04a0",
                "shop_id": "65890",
                "sku_id": 14784106,
                "special_tags": null,
                "spu_id": 14319725,
                "sub_title": "\u043e\u2018\u0408\u043e\u0497\u2116\u043e\u2018\u0408\u043e\u2018\u0408\u043e\u201d\u0498 | \u043e\u2022\u04a2.\u043e\u2018\u049b\u043e\u0497\u2116\u043e\u0497\u04a0\u043e\u2019\u2019\u043e\u2019\u0401",
                "tags": [
                    {
                        "background_color": "rgb(242,244,250)",
                        "logo": "",
                        "text": "\u0435\u04ae\u04b6\u0436\u2013\u00b0\u0438\u04aa\u04b0",
                        "text_color": "rgb(99,102,117)"
                    }
                ],
                "tags_v2": null,
                "title": "\u0435\u04ae\u04a2\u0436\u0451\u040e 2022\u0436\u00ac\u04ab \u0435\u04ae\u04a2\u0436\u0451\u040eL 280TSI DSG\u0439\u2026\u00b7\u0438\u04ab\u0408\u0437\u04af\u04b2",
                "transfer_cnt": 0
            },
            {
                "authentication_method": "\u0439\u049b\u04bb\u0435\u00ae\u04b3\u0436\u2013\u2116\u0438\u00ae\u04e8\u0438\u049c\u0492",
                "brand_id": 3,
                "brand_name": "\u0435\u0498\u201d\u0439\u00a9\u00b0",
                "brand_source_city_name": "\u0438\u0498\u049d\u0435\u00ae\u04af",
                "car_age": "",
                "car_id": 72284,
                "car_mileage": "",
                "car_name": "\u0434\u04d9\u04a2\u0436\u00ac\u040e\u0436\u201d\u2116\u0436\u00ac\u04ab E 300 L \u0436\u2014\u00b6\u0435\u00b0\u04a1\u0435\u04bb\u04e2 \u0438\u04aa\u049d\u0438\u04aa\u04b0",
                "car_source_city_name": "\u043e\u2018\u00b6\u043e\u2019\u04b1",
                "car_source_type": "\u0438\u04ae\u04d8\u0438\u0497\u0498",
                "car_year": 2022,
                "group_id": 7359361602698609203,
                "group_id_str": "7359361602698609203",
                "image": "https://p5-auto-sign.dcarimg.com/tos-cn-i-f042mdwyw7/86208699ed9f47ca80ec6e8ae44c8243~tplv-f042mdwyw7-auto-webp:480:0.jpg?rk3s=4892dee6&x-expires=1722650987&x-signature=EuKLzfw%2BrBiuUpYJMcIS8kAVed8%3D",
                "is_self_trade": false,
                "is_video": true,
                "official_hint_bar": "",
                "official_price": "\u043e\u0497\u049b\u043e\u04b8\u00ab.\u043e\u201c\u0408\u043e\u201c\u0408\u043e\u0497\u04a0",
                "platform_type": 0,
                "related_video_thumb": "",
                "series_id": 214,
                "series_name": "\u0435\u0498\u201d\u0439\u00a9\u00b0E\u0437\u04d9\u00a7",
                "sh_price": "\u043e\u2019\u049b\u043e\u04b8\u00ab.\u043e\u201d\u0499\u043e\u0497\u2116\u043e\u0497\u04a0",
                "shop_id": "61203",
                "sku_id": 14444258,
                "special_tags": null,
                "spu_id": 13985474,
                "sub_title": "\u043e\u2018\u0408\u043e\u0497\u2116\u043e\u2018\u0408\u043e\u2018\u0408\u043e\u201d\u0498 | \u043e\u2018\u0408.\u043e\u2022\u04a2\u043e\u0497\u2018\u043e\u0497\u04a0\u043e\u2019\u2019\u043e\u2019\u0401",
                "tags": [
                    {
                        "background_color": "rgba(179,125,18,0.1)",
                        "logo": "https://p3.dcarimg.com/img/tos-cn-i-dcdx/5f0015d5e1ee4547b51bc7544a06765c~noop.image",
                        "text": "\u0436\u0408\u0496\u0436\u04e9\u04e2\u0436\u04a0\u0498\u0435\u2018\u04a0",
                        "text_color": "rgba(179,125,18,1)"
                    }
                ],
                "tags_v2": null,
                "title": "\u0435\u0498\u201d\u0439\u00a9\u00b0E\u0437\u04d9\u00a7 2022\u0436\u00ac\u04ab \u0434\u04d9\u04a2\u0436\u00ac\u040e\u0436\u201d\u2116\u0436\u00ac\u04ab E 300 L \u0436\u2014\u00b6\u0435\u00b0\u04a1\u0435\u04bb\u04e2 \u0438\u04aa\u049d\u0438\u04aa\u04b0",
                "transfer_cnt": 1
            },
            {
                "authentication_method": "\u0436\u2014\u00a0\u0438\u00ae\u04e8\u0438\u049c\u0492",
                "brand_id": 12,
                "brand_name": "\u0435\u04b2\u00ab\u0435\u2026\u04e2",
                "brand_source_city_name": "\u0434\u0451\u04a0\u0436\u04e9\u00b7",
                "car_age": "",
                "car_id": 5057,
                "car_mileage": "",
                "car_name": "2.4L SIDI\u0438\u04b1\u04d8\u0439\u04e3\u2026\u0437\u04af\u04b2",
                "car_source_city_name": "\u043e\u2018\u04b9\u043e\u0497\u04b1",
                "car_source_type": "\u0438\u04ae\u04d8\u0438\u0497\u0498",
                "car_year": 2012,
                "group_id": 7352385942247718966,
                "group_id_str": "7352385942247718966",
                "image": "https://p5-auto-sign.dcarimg.com/tos-cn-i-f042mdwyw7/613a082b9baa47b2aeb5a8ba65360bf0~tplv-f042mdwyw7-auto-webp:480:0.jpg?rk3s=4892dee6&x-expires=1722650987&x-signature=GuhnM%2FVf8UvLvJMChvaX%2Bo5jzOw%3D",
                "is_self_trade": false,
                "is_video": true,
                "official_hint_bar": "",
                "official_price": "\u043e\u2018\u0408\u043e\u0497\u2018.\u043e\u0497\u2018\u043e\u2018\u049b\u043e\u0497\u04a0",
                "platform_type": 0,
                "related_video_thumb": "",
                "series_id": 347,
                "series_name": "\u0435\u0497\u04e3\u0438\u00b6\u04a0",
                "sh_price": "\u043e\u2018\u0408.\u043e\u2022\u04a2\u043e\u0497\u2018\u043e\u0497\u04a0",
                "shop_id": "1315",
                "sku_id": 14293791,
                "special_tags": null,
                "spu_id": 13838142,
                "sub_title": "\u043e\u2018\u0408\u043e\u0497\u2116\u043e\u2022\u04a2\u043e\u2018\u0408\u043e\u201d\u0498 | \u043e\u201c\u0408.\u043e\u201d\u0499\u043e\u0497\u2116\u043e\u0497\u04a0\u043e\u2019\u2019\u043e\u2019\u0401",
                "tags": [],
                "tags_v2": null,
                "title": "\u0435\u0497\u04e3\u0438\u00b6\u04a0 2012\u0436\u00ac\u04ab 2.4L SIDI\u0438\u04b1\u04d8\u0439\u04e3\u2026\u0437\u04af\u04b2",
                "transfer_cnt": 0
            },
            {
                "authentication_method": "\u0439\u049b\u04bb\u0435\u00ae\u04b3\u0436\u2013\u2116\u0438\u00ae\u04e8\u0438\u049c\u0492",
                "brand_id": 3,
                "brand_name": "\u0435\u0498\u201d\u0439\u00a9\u00b0",
                "brand_source_city_name": "\u0434\u0451\u04a3\u0438\u04ba\u04bb",
                "car_age": "",
                "car_id": 76236,
                "car_mileage": "",
                "car_name": "C 260 L \u0438\u049d\u0497\u0435\u04a0\u0401\u0437\u04af\u04b2",
                "car_source_city_name": "\u043e\u2019\u04b9\u0438\u04ba\u04bb",
                "car_source_type": "\u0438\u04ae\u04d8\u0438\u0497\u0498",
                "car_year": 2023,
                "group_id": 0,
                "group_id_str": "0",
                "image": "https://p5-auto-sign.dcarimg.com/tos-cn-i-f042mdwyw7/5aa58e5807df488b9883c830b25cc68c~tplv-f042mdwyw7-auto-webp:480:0.jpg?rk3s=4892dee6&x-expires=1722650987&x-signature=kC1HmpHfaS8XsgYRTqVroCrLdFE%3D",
                "is_self_trade": false,
                "is_video": false,
                "official_hint_bar": "",
                "official_price": "\u043e\u2019\u049b\u043e\u0497\u2018.\u043e\u2019\u049b\u043e\u0497\u2018\u043e\u0497\u04a0",
                "platform_type": 0,
                "related_video_thumb": "",
                "series_id": 212,
                "series_name": "\u0435\u0498\u201d\u0439\u00a9\u00b0C\u0437\u04d9\u00a7",
                "sh_price": "\u043e\u2018\u0408\u043e\u0497\u049b.\u043e\u201c\u0408\u043e\u0497\u2116\u043e\u0497\u04a0",
                "shop_id": "31574",
                "sku_id": 14255272,
                "special_tags": null,
                "spu_id": 13800132,
                "sub_title": "\u043e\u2018\u0408\u043e\u0497\u2116\u043e\u2018\u0408\u043e\u2019\u049b\u043e\u201d\u0498 | \u043e\u2022\u04a2.\u043e\u2022\u04a2\u043e\u0497\u2116\u043e\u0497\u04a0\u043e\u2019\u2019\u043e\u2019\u0401",
                "tags": [
                    {
                        "background_color": "rgba(179,125,18,0.1)",
                        "logo": "https://p3.dcarimg.com/img/tos-cn-i-dcdx/5f0015d5e1ee4547b51bc7544a06765c~noop.image",
                        "text": "\u0436\u0408\u0496\u0436\u04e9\u04e2\u0436\u04a0\u0498\u0435\u2018\u04a0",
                        "text_color": "rgba(179,125,18,1)"
                    },
                    {
                        "background_color": "rgb(242,244,250)",
                        "logo": "",
                        "text": "\u0435\u04ae\u04b6\u0436\u2013\u00b0\u0438\u04aa\u04b0",
                        "text_color": "rgb(99,102,117)"
                    }
                ],
                "tags_v2": null,
                "title": "\u0435\u0498\u201d\u0439\u00a9\u00b0C\u0437\u04d9\u00a7 2023\u0436\u00ac\u04ab C 260 L \u0438\u049d\u0497\u0435\u04a0\u0401\u0437\u04af\u04b2",
                "transfer_cnt": 0
            },
            {
                "authentication_method": "\u0439\u049b\u04bb\u0435\u00ae\u04b3\u0436\u2013\u2116\u0438\u00ae\u04e8\u0438\u049c\u0492",
                "brand_id": 2,
                "brand_name": "\u0435\u0498\u0498\u0438\u049d\u04d8",
                "brand_source_city_name": "\u0436\u04e9\u04ba\u0435\u049a\u2014",
                "car_age": "",
                "car_id": 44670,
                "car_mileage": "",
                "car_name": "45 TFSI \u0438\u04ae\u00bb\u0439\u0496\u04af\u0435\u04a0\u0401\u0436\u201e\u04b9\u0435\u04bb\u04e2",
                "car_source_city_name": "\u0436\u04e9\u04ba\u0435\u049a\u2014",
                "car_source_type": "\u0438\u04ae\u04d8\u0438\u0497\u0498",
                "car_year": 2020,
                "group_id": 0,
                "group_id_str": "0",
                "image": "https://p5-auto-sign.dcarimg.com/tos-cn-i-f042mdwyw7/d02a7535ae4e433ba4648e58b5d0516b~tplv-f042mdwyw7-auto-webp:480:0.jpg?rk3s=4892dee6&x-expires=1722650987&x-signature=jLUIVW6l%2BpcS6wjW%2BisXONLmM%2BY%3D",
                "is_self_trade": false,
                "is_video": false,
                "official_hint_bar": "",
                "official_price": "\u043e\u0497\u049b\u043e\u2019\u049b.\u043e\u2018\u049b\u043e\u201c\u0408\u043e\u0497\u04a0",
                "platform_type": 0,
                "related_video_thumb": "",
                "series_id": 99,
                "series_name": "\u0435\u0498\u0498\u0438\u049d\u04d8A6L",
                "sh_price": "\u043e\u2018\u0408\u043e\u0497\u2018.\u043e\u0497\u2018\u043e\u2022\u04a2\u043e\u0497\u04a0",
                "shop_id": "4250",
                "sku_id": 14052951,
                "special_tags": null,
                "spu_id": 13600582,
                "sub_title": "\u043e\u2018\u0408\u043e\u0497\u2116\u043e\u2018\u0408\u043e\u0497\u2116\u043e\u201d\u0498 | \u043e\u2022\u04a2\u043e\u2022\u04a2.\u043e\u2018\u0408\u043e\u2019\u049b\u043e\u0497\u04a0\u043e\u2019\u2019\u043e\u2019\u0401",
                "tags": [
                    {
                        "background_color": "rgba(179,125,18,0.1)",
                        "logo": "https://p3.dcarimg.com/img/tos-cn-i-dcdx/5f0015d5e1ee4547b51bc7544a06765c~noop.image",
                        "text": "\u0436\u0408\u0496\u0436\u04e9\u04e2\u0436\u04a0\u0498\u0435\u2018\u04a0",
                        "text_color": "rgba(179,125,18,1)"
                    }
                ],
                "tags_v2": null,
                "title": "\u0435\u0498\u0498\u0438\u049d\u04d8A6L 2020\u0436\u00ac\u04ab 45 TFSI \u0438\u04ae\u00bb\u0439\u0496\u04af\u0435\u04a0\u0401\u0436\u201e\u04b9\u0435\u04bb\u04e2",
                "transfer_cnt": 1
            },
            {
                "authentication_method": "\u0436\u2014\u00a0\u0438\u00ae\u04e8\u0438\u049c\u0492",
                "brand_id": 2,
                "brand_name": "\u0435\u0498\u0498\u0438\u049d\u04d8",
                "brand_source_city_name": "\u0435\u04a2\u2014\u0434\u04d9\u00ac",
                "car_age": "",
                "car_id": 80117,
                "car_mileage": "",
                "car_name": "45 TFSI quattro S line\u0438\u049d\u0497\u0435\u04a0\u0401\u0435\u04bb\u04e2",
                "car_source_city_name": "\u0435\u04a2\u2014\u0434\u04d9\u00ac",
                "car_source_type": "\u0438\u04ae\u04d8\u0438\u0497\u0498",
                "car_year": 2023,
                "group_id": 0,
                "group_id_str": "0",
                "image": "https://p5-auto-sign.dcarimg.com/tos-cn-i-f042mdwyw7/f5ce1c870d8847f2855866d7c1121b98~tplv-f042mdwyw7-auto-webp:480:0.jpg?rk3s=4892dee6&x-expires=1722650987&x-signature=vd3qTlEPiJ%2BxcvkvbgFRIGL%2F1%2Fw%3D",
                "is_self_trade": false,
                "is_video": false,
                "official_hint_bar": "",
                "official_price": "\u043e\u201d\u0499\u043e\u2019\u049b.\u043e\u2018\u0408\u043e\u201c\u0408\u043e\u0497\u04a0",
                "platform_type": 0,
                "related_video_thumb": "",
                "series_id": 87,
                "series_name": "\u0435\u0498\u0498\u0438\u049d\u04d8Q7",
                "sh_price": "\u043e\u0497\u049b\u043e\u0497\u049b.\u043e\u0497\u2018\u043e\u201c\u0408\u043e\u0497\u04a0",
                "shop_id": "5233",
                "sku_id": 15522756,
                "special_tags": null,
                "spu_id": 15043326,
                "sub_title": "\u043e\u2018\u0408\u043e\u0497\u2116\u043e\u2018\u0408\u043e\u2019\u049b\u043e\u201d\u0498 | \u043e\u0497\u2116.\u043e\u2019\u049b\u043e\u0497\u049b\u043e\u0497\u04a0\u043e\u2019\u2019\u043e\u2019\u0401",
                "tags": [
                    {
                        "background_color": "rgb(242,244,250)",
                        "logo": "",
                        "text": "\u0435\u04ae\u04b6\u0436\u2013\u00b0\u0438\u04aa\u04b0",
                        "text_color": "rgb(99,102,117)"
                    }
                ],
                "tags_v2": null,
                "title": "\u0435\u0498\u0498\u0438\u049d\u04d8Q7 2023\u0436\u00ac\u04ab 45 TFSI quattro S line\u0438\u049d\u0497\u0435\u04a0\u0401\u0435\u04bb\u04e2",
                "transfer_cnt": 0
            },
            {
                "authentication_method": "\u0436\u2014\u00a0\u0438\u00ae\u04e8\u0438\u049c\u0492",
                "brand_id": 1,
                "brand_name": "\u0435\u04e8\u00a7\u0434\u0458\u2014",
                "brand_source_city_name": "\u0436\u049b\u04ef\u0435\u00b7\u04bb",
                "car_age": "",
                "car_id": 40860,
                "car_mileage": "",
                "car_name": "\u0435\u00ae\u049b\u0436\u049b\u0498\u0412\u00b7\u0434\u0458\u00a0\u0435\u0498\u04ae 1.5L \u0438\u04ae\u04d8\u0435\u04a0\u0401\u0436\u2014\u00b6\u0435\u00b0\u04a1\u0435\u04bb\u04e2 \u0435\u04e3\u04aaVI",
                "car_source_city_name": "\u0436\u049b\u04ef\u0435\u00b7\u04bb",
                "car_source_type": "\u0438\u04ae\u04d8\u0438\u0497\u0498",
                "car_year": 2019,
                "group_id": 0,
                "group_id_str": "0",
                "image": "https://p5-auto-sign.dcarimg.com/tos-cn-i-f042mdwyw7/07bb398dbd754817872010bfdd17744e~tplv-f042mdwyw7-auto-webp:480:0.jpg?rk3s=4892dee6&x-expires=1722650987&x-signature=%2F8fiFdBjsK5SA1k13LIquAVQ5jg%3D",
                "is_self_trade": false,
                "is_video": false,
                "official_hint_bar": "",
                "official_price": "\u043e\u2022\u04a2\u043e\u0497\u2116.\u043e\u201c\u0408\u043e\u201c\u0408\u043e\u0497\u04a0",
                "platform_type": 0,
                "related_video_thumb": "",
                "series_id": 409,
                "series_name": "\u0435\u00ae\u049b\u0436\u049b\u0498",
                "sh_price": "\u043e\u0497\u2018.\u043e\u201c\u0408\u043e\u201c\u0408\u043e\u0497\u04a0",
                "shop_id": "1868",
                "sku_id": 15499201,
                "special_tags": null,
                "spu_id": 15020299,
                "sub_title": "\u043e\u2018\u0408\u043e\u0497\u2116\u043e\u2018\u0408\u043e\u2018\u0408\u043e\u201d\u0498 | \u043e\u2018\u0408.\u043e\u2018\u0408\u043e\u0497\u2116\u043e\u0497\u04a0\u043e\u2019\u2019\u043e\u2019\u0401",
                "tags": [
                    {
                        "background_color": "rgb(242,244,250)",
                        "logo": "",
                        "text": "\u0435\u04ae\u04b6\u0436\u2013\u00b0\u0438\u04aa\u04b0",
                        "text_color": "rgb(99,102,117)"
                    }
                ],
                "tags_v2": null,
                "title": "\u0435\u00ae\u049b\u0436\u049b\u0498 2019\u0436\u00ac\u04ab \u0435\u00ae\u049b\u0436\u049b\u0498\u0412\u00b7\u0434\u0458\u00a0\u0435\u0498\u04ae 1.5L \u0438\u04ae\u04d8\u0435\u04a0\u0401\u0436\u2014\u00b6\u0435\u00b0\u04a1\u0435\u04bb\u04e2 \u0435\u04e3\u04aaVI",
                "transfer_cnt": 1
            },
            {
                "authentication_method": "\u0436\u2014\u00a0\u0438\u00ae\u04e8\u0438\u049c\u0492",
                "brand_id": 2,
                "brand_name": "\u0435\u0498\u0498\u0438\u049d\u04d8",
                "brand_source_city_name": "\u0436\u0493\u00a0\u0435\u00b7\u04bb",
                "car_age": "",
                "car_id": 49133,
                "car_mileage": "",
                "car_name": "35 TFSI \u0436\u2014\u00b6\u0435\u00b0\u04a1\u0438\u04ae\u0499\u0439\u04e3\u2026\u0435\u04bb\u04e2",
                "car_source_city_name": "\u0436\u0493\u00a0\u0435\u00b7\u04bb",
                "car_source_type": "\u0438\u04ae\u04d8\u0438\u0497\u0498",
                "car_year": 2021,
                "group_id": 0,
                "group_id_str": "0",
                "image": "https://p5-auto-sign.dcarimg.com/tos-cn-i-f042mdwyw7/8b4dd9cd26bf49f1bf97a8aa349bc82e~tplv-f042mdwyw7-auto-webp:480:0.jpg?rk3s=4892dee6&x-expires=1722650987&x-signature=351nBYqCQpNC3Uj%2Fmk0sCxr9rik%3D",
                "is_self_trade": false,
                "is_video": false,
                "official_hint_bar": "",
                "official_price": "\u043e\u2018\u0408\u043e\u201c\u0408.\u043e\u04b8\u00ab\u043e\u201c\u0408\u043e\u0497\u04a0",
                "platform_type": 0,
                "related_video_thumb": "",
                "series_id": 100,
                "series_name": "\u0435\u0498\u0498\u0438\u049d\u04d8Q3",
                "sh_price": "\u043e\u2022\u04a2\u043e\u2022\u04a2.\u043e\u2018\u049b\u043e\u2018\u049b\u043e\u0497\u04a0",
                "shop_id": "33273",
                "sku_id": 15461855,
                "special_tags": null,
                "spu_id": 14983901,
                "sub_title": "\u043e\u2018\u0408\u043e\u0497\u2116\u043e\u2018\u0408\u043e\u2022\u04a2\u043e\u201d\u0498 | \u043e\u2018\u049b.\u043e\u0497\u049b\u043e\u0497\u2116\u043e\u0497\u04a0\u043e\u2019\u2019\u043e\u2019\u0401",
                "tags": [],
                "tags_v2": null,
                "title": "\u0435\u0498\u0498\u0438\u049d\u04d8Q3 2021\u0436\u00ac\u04ab 35 TFSI \u0436\u2014\u00b6\u0435\u00b0\u04a1\u0438\u04ae\u0499\u0439\u04e3\u2026\u0435\u04bb\u04e2",
                "transfer_cnt": 0
            },
            {
                "authentication_method": "\u0436\u2014\u00a0\u0438\u00ae\u04e8\u0438\u049c\u0492",
                "brand_id": 242,
                "brand_name": "\u0435\u04b9\u0493\u0435\u00ae\u04af",
                "brand_source_city_name": "\u0436\u00b7\u04b1\u0435\u04a3\u0456",
                "car_age": "",
                "car_id": 54690,
                "car_mileage": "",
                "car_name": "Plus 80 \u0438\u00b6\u2026\u0439\u2022\u049d\u0437\u00bb\u04ef\u0438\u04b2\u04d8\u0437\u04af\u04b2",
                "car_source_city_name": "\u0436\u00b7\u04b1\u0435\u04a3\u0456",
                "car_source_type": "\u0438\u04ae\u04d8\u0438\u0497\u0498",
                "car_year": 2021,
                "group_id": 0,
                "group_id_str": "0",
                "image": "https://p5-auto-sign.dcarimg.com/tos-cn-i-f042mdwyw7/c9318c1a9a3e4ad48ba42ab39bcb90aa~tplv-f042mdwyw7-auto-webp:480:0.jpg?rk3s=4892dee6&x-expires=1722650987&x-signature=8YcuzHwF5YnaHGEbIflfKTKSoCA%3D",
                "is_self_trade": false,
                "is_video": false,
                "official_hint_bar": "",
                "official_price": "\u043e\u2022\u04a2\u043e\u0497\u2018.\u043e\u2018\u049b\u043e\u201d\u0499\u043e\u0497\u04a0",
                "platform_type": 0,
                "related_video_thumb": "",
                "series_id": 3101,
                "series_name": "AION S",
                "sh_price": "\u043e\u2018\u049b.\u043e\u2018\u0408\u043e\u201c\u0408\u043e\u0497\u04a0",
                "shop_id": "51147",
                "sku_id": 15428056,
                "special_tags": null,
                "spu_id": 14950662,
                "sub_title": "\u043e\u2018\u0408\u043e\u0497\u2116\u043e\u2018\u0408\u043e\u2018\u0408\u043e\u201d\u0498 | \u043e\u0497\u2018.\u043e\u04b8\u00ab\u043e\u0497\u2116\u043e\u0497\u04a0\u043e\u2019\u2019\u043e\u2019\u0401",
                "tags": [],
                "tags_v2": null,
                "title": "AION S 2021\u0436\u00ac\u04ab Plus 80 \u0438\u00b6\u2026\u0439\u2022\u049d\u0437\u00bb\u04ef\u0438\u04b2\u04d8\u0437\u04af\u04b2",
                "transfer_cnt": 0
            }
        ],
        "total": 10000
    },
    "message": "success",
    "prompts": "",
    "status": 0
}